angular_range_ops/__init__.py
angular_range_ops-0.1.0.dist-info/licenses/LICENSE
angular_range_ops-0.1.0.dist-info/METADATA
angular_range_ops-0.1.0.dist-info/WHEEL
angular_range_ops-0.1.0.dist-info/top_level.txt
angular_range_ops-0.1.0.dist-info/RECORD
